{
"meta":{"test_sets":[],"test_metrics":[],"learn_metrics":[{"best_value":"Min","name":"RMSE"}],"launch_mode":"Train","parameters":"","iteration_count":100,"learn_sets":["learn"],"name":"experiment"},
"iterations":[
{"learn":[14.005006],"iteration":0,"passed_time":0.001010143608,"remaining_time":0.1000042172},
{"learn":[13.14441192],"iteration":1,"passed_time":0.001801224394,"remaining_time":0.08825999532},
{"learn":[12.34258257],"iteration":2,"passed_time":0.002566256091,"remaining_time":0.08297561361},
{"learn":[11.64527793],"iteration":3,"passed_time":0.003202104343,"remaining_time":0.07685050422},
{"learn":[11.02766183],"iteration":4,"passed_time":0.004015407006,"remaining_time":0.0762927331},
{"learn":[10.43485794],"iteration":5,"passed_time":0.00480023601,"remaining_time":0.07520369749},
{"learn":[9.890641275],"iteration":6,"passed_time":0.005895320642,"remaining_time":0.07832354567},
{"learn":[9.492161212],"iteration":7,"passed_time":0.006772613894,"remaining_time":0.07788505979},
{"learn":[9.105082953],"iteration":8,"passed_time":0.007658803913,"remaining_time":0.07743901734},
{"learn":[8.674157135],"iteration":9,"passed_time":0.008600929342,"remaining_time":0.07740836407},
{"learn":[8.341743544],"iteration":10,"passed_time":0.009613727953,"remaining_time":0.07778379889},
{"learn":[8.049372916],"iteration":11,"passed_time":0.01048125184,"remaining_time":0.07686251352},
{"learn":[7.757318612],"iteration":12,"passed_time":0.01132045427,"remaining_time":0.07575996317},
{"learn":[7.522206899],"iteration":13,"passed_time":0.01217782999,"remaining_time":0.07480666991},
{"learn":[7.297756655],"iteration":14,"passed_time":0.01298019108,"remaining_time":0.0735544161},
{"learn":[7.088359431],"iteration":15,"passed_time":0.01381422376,"remaining_time":0.07252467473},
{"learn":[6.882113791],"iteration":16,"passed_time":0.01473215359,"remaining_time":0.07192757341},
{"learn":[6.704728832],"iteration":17,"passed_time":0.01554487516,"remaining_time":0.07081554238},
{"learn":[6.563881962],"iteration":18,"passed_time":0.01636794623,"remaining_time":0.06977913919},
{"learn":[6.418790279],"iteration":19,"passed_time":0.01759952713,"remaining_time":0.07039810854},
{"learn":[6.315756953],"iteration":20,"passed_time":0.01839304155,"remaining_time":0.06919287061},
{"learn":[6.210157751],"iteration":21,"passed_time":0.01915532808,"remaining_time":0.067914345},
{"learn":[6.115058449],"iteration":22,"passed_time":0.01995044743,"remaining_time":0.06679062834},
{"learn":[6.014819884],"iteration":23,"passed_time":0.02075496353,"remaining_time":0.06572405118},
{"learn":[5.93117229],"iteration":24,"passed_time":0.0217113859,"remaining_time":0.06513415771},
{"learn":[5.844857622],"iteration":25,"passed_time":0.02258681564,"remaining_time":0.06428555222},
{"learn":[5.771145213],"iteration":26,"passed_time":0.02340167028,"remaining_time":0.06327118261},
{"learn":[5.704018229],"iteration":27,"passed_time":0.02415849651,"remaining_time":0.06212184817},
{"learn":[5.665806474],"iteration":28,"passed_time":0.02504210166,"remaining_time":0.06130997303},
{"learn":[5.616500369],"iteration":29,"passed_time":0.02584009643,"remaining_time":0.06029355833},
{"learn":[5.558023666],"iteration":30,"passed_time":0.02664856999,"remaining_time":0.05931455901},
{"learn":[5.510080976],"iteration":31,"passed_time":0.02741186842,"remaining_time":0.05825022039},
{"learn":[5.468747792],"iteration":32,"passed_time":0.02827008572,"remaining_time":0.05739684071},
{"learn":[5.429275534],"iteration":33,"passed_time":0.02904293119,"remaining_time":0.05637745467},
{"learn":[5.402117324],"iteration":34,"passed_time":0.02987668239,"remaining_time":0.0554852673},
{"learn":[5.367635151],"iteration":35,"passed_time":0.0306955255,"remaining_time":0.0545698231},
{"learn":[5.345181232],"iteration":36,"passed_time":0.03148451234,"remaining_time":0.05360876425},
{"learn":[5.319151269],"iteration":37,"passed_time":0.03220827626,"remaining_time":0.05255034548},
{"learn":[5.296134146],"iteration":38,"passed_time":0.03304047549,"remaining_time":0.05167869243},
{"learn":[5.269629003],"iteration":39,"passed_time":0.03388466541,"remaining_time":0.05082699811},
{"learn":[5.251147059],"iteration":40,"passed_time":0.03475221124,"remaining_time":0.05000927959},
{"learn":[5.248003302],"iteration":41,"passed_time":0.03518202026,"remaining_time":0.04858469465},
{"learn":[5.232376509],"iteration":42,"passed_time":0.03611343551,"remaining_time":0.04787129823},
{"learn":[5.213524255],"iteration":43,"passed_time":0.03694676687,"remaining_time":0.04702315783},
{"learn":[5.189691584],"iteration":44,"passed_time":0.03776565005,"remaining_time":0.04615801672},
{"learn":[5.166052198],"iteration":45,"passed_time":0.03864428583,"remaining_time":0.04536503119},
{"learn":[5.140406659],"iteration":46,"passed_time":0.0394218812,"remaining_time":0.04445446178},
{"learn":[5.118929684],"iteration":47,"passed_time":0.04025893768,"remaining_time":0.04361384915},
{"learn":[5.108792602],"iteration":48,"passed_time":0.0410381771,"remaining_time":0.04271320474},
{"learn":[5.098141225],"iteration":49,"passed_time":0.04190280649,"remaining_time":0.04190280649},
{"learn":[5.085926393],"iteration":50,"passed_time":0.04268120242,"remaining_time":0.04100742977},
{"learn":[5.067816804],"iteration":51,"passed_time":0.04348576957,"remaining_time":0.04014071037},
{"learn":[5.049834901],"iteration":52,"passed_time":0.044311686,"remaining_time":0.03929526872},
{"learn":[5.03838627],"iteration":53,"passed_time":0.04519638321,"remaining_time":0.03850062273},
{"learn":[5.033534248],"iteration":54,"passed_time":0.04570453988,"remaining_time":0.03739462353},
{"learn":[5.023726885],"iteration":55,"passed_time":0.0464902014,"remaining_time":0.03652801539},
{"learn":[5.01290392],"iteration":56,"passed_time":0.04728196347,"remaining_time":0.03566884964},
{"learn":[5.005569127],"iteration":57,"passed_time":0.04814732424,"remaining_time":0.03486530376},
{"learn":[4.989969032],"iteration":58,"passed_time":0.04893578914,"remaining_time":0.03400622635},
{"learn":[4.976762446],"iteration":59,"passed_time":0.04986480081,"remaining_time":0.03324320054},
{"learn":[4.967222715],"iteration":60,"passed_time":0.05099204509,"remaining_time":0.03260147145},
{"learn":[4.954407599],"iteration":61,"passed_time":0.05196124154,"remaining_time":0.03184721255},
{"learn":[4.942125056],"iteration":62,"passed_time":0.0527837005,"remaining_time":0.03099995109},
{"learn":[4.930230716],"iteration":63,"passed_time":0.05367671433,"remaining_time":0.03019315181},
{"learn":[4.921695642],"iteration":64,"passed_time":0.05456182136,"remaining_time":0.02937944227},
{"learn":[4.906405625],"iteration":65,"passed_time":0.05545766051,"remaining_time":0.02856909784},
{"learn":[4.894330248],"iteration":66,"passed_time":0.05629349564,"remaining_time":0.02772664711},
{"learn":[4.88211557],"iteration":67,"passed_time":0.05714922826,"remaining_time":0.02689375448},
{"learn":[4.877946398],"iteration":68,"passed_time":0.05792142346,"remaining_time":0.02602266851},
{"learn":[4.863182126],"iteration":69,"passed_time":0.05878868686,"remaining_time":0.02519515151},
{"learn":[4.84646533],"iteration":70,"passed_time":0.05966322587,"remaining_time":0.02436948662},
{"learn":[4.838014752],"iteration":71,"passed_time":0.06051460934,"remaining_time":0.02353345919},
{"learn":[4.82981137],"iteration":72,"passed_time":0.06133680877,"remaining_time":0.02268621694},
{"learn":[4.817094767],"iteration":73,"passed_time":0.06212877218,"remaining_time":0.02182902806},
{"learn":[4.808314151],"iteration":74,"passed_time":0.06289873316,"remaining_time":0.02096624439},
{"learn":[4.796235023],"iteration":75,"passed_time":0.06368715894,"remaining_time":0.0201117344},
{"learn":[4.784434534],"iteration":76,"passed_time":0.06453442561,"remaining_time":0.01927651674},
{"learn":[4.774402487],"iteration":77,"passed_time":0.06532584609,"remaining_time":0.01842523864},
{"learn":[4.76731896],"iteration":78,"passed_time":0.06622467087,"remaining_time":0.01760402643},
{"learn":[4.75934113],"iteration":79,"passed_time":0.06714586685,"remaining_time":0.01678646671},
{"learn":[4.754106378],"iteration":80,"passed_time":0.06791522575,"remaining_time":0.01593073197},
{"learn":[4.744002932],"iteration":81,"passed_time":0.06874610153,"remaining_time":0.01509060765},
{"learn":[4.731700554],"iteration":82,"passed_time":0.06960648387,"remaining_time":0.01425674971},
{"learn":[4.723284153],"iteration":83,"passed_time":0.07043123811,"remaining_time":0.01341547393},
{"learn":[4.712232782],"iteration":84,"passed_time":0.07121754991,"remaining_time":0.01256780293},
{"learn":[4.703046867],"iteration":85,"passed_time":0.07203273612,"remaining_time":0.01172625937},
{"learn":[4.698601855],"iteration":86,"passed_time":0.07281571164,"remaining_time":0.01088050864},
{"learn":[4.692429407],"iteration":87,"passed_time":0.0736844979,"remaining_time":0.01004788608},
{"learn":[4.675027364],"iteration":88,"passed_time":0.07449234123,"remaining_time":0.009206918579},
{"learn":[4.662368584],"iteration":89,"passed_time":0.07531857732,"remaining_time":0.008368730813},
{"learn":[4.646206172],"iteration":90,"passed_time":0.07617242734,"remaining_time":0.00753353677},
{"learn":[4.641245848],"iteration":91,"passed_time":0.07694405146,"remaining_time":0.006690787084},
{"learn":[4.633900435],"iteration":92,"passed_time":0.07779836045,"remaining_time":0.005855790571},
{"learn":[4.624738236],"iteration":93,"passed_time":0.07869969997,"remaining_time":0.005023385104},
{"learn":[4.612798287],"iteration":94,"passed_time":0.07963442144,"remaining_time":0.004191285339},
{"learn":[4.605222001],"iteration":95,"passed_time":0.080543715,"remaining_time":0.003355988125},
{"learn":[4.601725912],"iteration":96,"passed_time":0.0814627159,"remaining_time":0.00251946544},
{"learn":[4.59722371],"iteration":97,"passed_time":0.082215224,"remaining_time":0.001677861714},
{"learn":[4.580235665],"iteration":98,"passed_time":0.08297882299,"remaining_time":0.0008381699292},
{"learn":[4.57591791],"iteration":99,"passed_time":0.08376876258,"remaining_time":0}
]}